paraforge/__init__.py
paraforge/libparaforge.so
paraforge-0.0.3.dist-info/METADATA
paraforge-0.0.3.dist-info/WHEEL
paraforge-0.0.3.dist-info/top_level.txt
paraforge-0.0.3.dist-info/RECORD
