Metadata-Version: 2.1
Name: paraforge
Version: 0.0.3
Summary: Evaluation of a Python-Rust architecture for a parametric modeling project
Home-page: https://github.com/Densaugeo/paraforge
Author: Densaugeo
Author-email: author@example.com
Classifier: Programming Language :: Python :: 3
Classifier: Programming Language :: Rust
Classifier: Operating System :: POSIX :: Linux
Requires-Python: >=3.12
Requires-Dist: cffi
